pyocient/__init__.py
pyocient/api.py
pyocient/cli.py
pyocient/datetime_ns.py
pyocient/ocient_protocol_pb2.py
pyocient/pkg_version.py
pyocient/py.typed
pyocient/sso.py
pyocient-3.5.1.dist-info/WHEEL
pyocient-3.5.1.dist-info/METADATA
pyocient-3.5.1.dist-info/entry_points.txt
pyocient-3.5.1.dist-info/RECORD
