Metadata-Version: 2.1
Name: pyocient
Author: Ocient Inc
Author-email: info@ocient.com
Home-page: https://www.ocient.com/
License: Apache License, Version 2.0
Summary: Ocient Hyperscale Data Warehouse DBAPI Driver
Project-URL: documentation, https://docs.ocient.com/
Project-URL: release_notes, https://github.com/ocient/pyocient_release/
Classifier: Development Status :: 5 - Production/Stable
Classifier: Topic :: Database
Classifier: Topic :: Database :: Front-Ends
Classifier: Topic :: Software Development
Classifier: Topic :: Software Development :: Libraries :: Python Modules
Classifier: Intended Audience :: Developers
Classifier: License :: OSI Approved :: Apache Software License
Classifier: Typing :: Typed
Requires-Python: >=3.10,<4
Requires-Dist: asn1
Requires-Dist: cryptography
Requires-Dist: dsnparse<=0.1.15
Requires-Dist: pkce
Requires-Dist: prompt-toolkit
Requires-Dist: pygments
Requires-Dist: pyparsing~=3.1
Requires-Dist: requests
Requires-Dist: tabulate
Requires-Dist: typing_extensions
Requires-Dist: protobuf>=5.29.2
Version: 3.5.1
